{
    "A": {
        "x": 1311,
        "y": 648,
        "type": 1,
        "orientation": 0
    },
    "B": {
        "x": 834,
        "y": 607,
        "type": 1,
        "orientation": 0
    },
    "C": {
        "x": 1066,
        "y": 437,
        "type": 1,
        "orientation": 0
    },
    "D": {
        "x": 900,
        "y": 404,
        "type": 1,
        "orientation": 0
    },
    "E": {
        "x": 912,
        "y": 117,
        "type": 1,
        "orientation": 0
    },
    "F": {
        "x": 704,
        "y": 86,
        "type": 1,
        "orientation": 0
    }
}